saludador/__init__.py
saludador/launcher/__author__.py
saludador/launcher/__init__.py
saludador/launcher/__main__.py
saludador/launcher/__version__.py
saludador/modules/__init__.py
saludador/resources/__init__.py
saluda-0.0.1.dist-info/LICENSE
saluda-0.0.1.dist-info/METADATA
saluda-0.0.1.dist-info/WHEEL
saluda-0.0.1.dist-info/entry_points.txt
saluda-0.0.1.dist-info/top_level.txt
saluda-0.0.1.dist-info/RECORD
