Metadata-Version: 2.1
Name: saluda
Version: 0.0.1
Summary: Paquete de pruebas
Home-page: https://github.com/jaimefeldman/saludador
Author: jimix
Author-email: jaimefel@arjancodes.com
License: MIT
Classifier: License :: OSI Approved :: MIT License
Classifier: Programming Language :: Python :: 3.10
Classifier: Operating System :: OS Independent
Requires-Python: >=3.10
License-File: LICENSE
Requires-Dist: rich >=13.5.3
Provides-Extra: dev
Requires-Dist: pytest >=7.0 ; extra == 'dev'
Requires-Dist: twine >=4.0.2 ; extra == 'dev'
